<?xml version="1.0" encoding="UTF-8"?>
<!-- Generated by JClic - https://projectestac.github.io/jclic -->
<manifest identifier="JClic-5EE516" version="1.0" xmlns="http://www.imsproject.org/xsd/imscp_rootv1p1p2" xmlns:adlcp="http://www.adlnet.org/xsd/adlcp_rootv1p2" xmlns:xsi="http://www.w3.org/2001/XMLSchema-instance" xsi:schemaLocation= "http://www.imsproject.org/xsd/imscp_rootv1p1p2 imscp_rootv1p1p2.xsd http://www.imsglobal.org/xsd/imsmd_rootv1p2p1 imsmd_rootv1p2p1.xsd http://www.adlnet.org/xsd/adlcp_rootv1p2 adlcp_rootv1p2.xsd">
 <metadata> 
  <schema>ADL SCORM</schema>
  <schemaversion>1.2</schemaversion>
 </metadata> 
 <organizations default="JClic">  
  <organization identifier="JClic">  
   <title>Jules01f</title>
   <item identifier="ITEM_JClic-5EE516" identifierref="RES_JClic-5EE516">
    <title>Jules01f</title>
   </item>
  </organization>
 </organizations>
 <resources>
  <resource identifier="RES_JClic-5EE516" type="webcontent" href="/index.html" adlcp:scormtype="sco"> 
   <file href="applausejules_.mp3"/>
   <file href="cowboyhoed.jpg"/>
   <file href="cowboyhoedschaduw.jpg"/>
   <file href="favicon.ico"/>
   <file href="hoed.jpg"/>
   <file href="hoedschaduw.jpg"/>
   <file href="icon-192.png"/>
   <file href="icon-72.png"/>
   <file href="imsmanifest.xml"/>
   <file href="index.html"/>
   <file href="jules01f.jclic"/>
   <file href="jules01f.jclic.js"/>
   <file href="julesachtergrondjpg.jpg"/>
   <file href="julesbgeel.jpg"/>
   <file href="julesbgroen.jpg"/>
   <file href="julesblauw.jpg"/>
   <file href="julesclown.jpg"/>
   <file href="julesrood.jpg"/>
   <file href="julesverkleed.jpg"/>
   <file href="kroon.jpg"/>
   <file href="kroonschaduw.jpg"/>
   <file href="marie_verkleed.jpg"/>
   <file href="mutsblauw.jpg"/>
   <file href="mutsgeel.jpg"/>
   <file href="mutsgroen.jpg"/>
   <file href="mutsrood.jpg"/>
   <file href="narrenkap.jpg"/>
   <file href="narrenkapschauw.jpg"/>
   <file href="project-cover.jpg"/>
   <file href="project-thumb.jpg"/>
   <file href="project.json"/>
   <file href="puzzelcarnaval.jpg"/>
   <file href="puzzelcarnaval2.jpg"/>
   <file href="trommel.jpg"/>
  </resource>
 </resources>
</manifest>