<?xml version="1.0" encoding="UTF-8"?>
<!-- Generated by JClic - https://projectestac.github.io/jclic -->
<manifest identifier="JClic-F9220F" version="1.0" xmlns="http://www.imsproject.org/xsd/imscp_rootv1p1p2" xmlns:adlcp="http://www.adlnet.org/xsd/adlcp_rootv1p2" xmlns:xsi="http://www.w3.org/2001/XMLSchema-instance" xsi:schemaLocation= "http://www.imsproject.org/xsd/imscp_rootv1p1p2 imscp_rootv1p1p2.xsd http://www.imsglobal.org/xsd/imsmd_rootv1p2p1 imsmd_rootv1p2p1.xsd http://www.adlnet.org/xsd/adlcp_rootv1p2 adlcp_rootv1p2.xsd">
 <metadata> 
  <schema>ADL SCORM</schema>
  <schemaversion>1.2</schemaversion>
 </metadata> 
 <organizations default="JClic">  
  <organization identifier="JClic">  
   <title>Herfst02a</title>
   <item identifier="ITEM_JClic-F9220F" identifierref="RES_JClic-F9220F">
    <title>Herfst02a</title>
   </item>
  </organization>
 </organizations>
 <resources>
  <resource identifier="RES_JClic-F9220F" type="webcontent" href="/index.html" adlcp:scormtype="sco"> 
   <file href="achtergrondherfst.jpg"/>
   <file href="applauseherfst.mp3"/>
   <file href="egel_klein.jpg"/>
   <file href="egel_kleiner.jpg"/>
   <file href="egel_kleinst.jpg"/>
   <file href="favicon.ico"/>
   <file href="geelpaddenstoel1stip.jpg"/>
   <file href="geelpaddenstoel2stip.jpg"/>
   <file href="geelpaddenstoel3stip.jpg"/>
   <file href="geelpaddenstoel4stip.jpg"/>
   <file href="groot_egel.jpg"/>
   <file href="herfst02a.jclic"/>
   <file href="herfst02a.jclic.js"/>
   <file href="icon-192.png"/>
   <file href="icon-72.png"/>
   <file href="imsmanifest.xml"/>
   <file href="index.html"/>
   <file href="kabotuer_ster_jpg.jpg"/>
   <file href="kabouter__stipjes.jpg"/>
   <file href="kabouter_blaadjes.jpg"/>
   <file href="kabouter_blauw_jpg.jpg"/>
   <file href="kabouter_bloem.jpg"/>
   <file href="kabouter_egel_jpg.jpg"/>
   <file href="kabouter_eikel.jpg"/>
   <file href="kabouter_groen.jpg"/>
   <file href="kabouter_hartjejpg.jpg"/>
   <file href="paddenstoe2stip.jpg"/>
   <file href="paddenstoe3stip.jpg"/>
   <file href="paddenstoel1stip.jpg"/>
   <file href="paddenstoel4stip.jpg"/>
   <file href="paddenstoel_blaadjes.jpg"/>
   <file href="paddenstoel_blauw_jpg.jpg"/>
   <file href="paddenstoel_bloem.jpg"/>
   <file href="paddenstoel_egel_jpg.jpg"/>
   <file href="paddenstoel_eikel.jpg"/>
   <file href="paddenstoel_groen.jpg"/>
   <file href="paddenstoel_hartjejpg.jpg"/>
   <file href="paddenstoel_ster_jpg.jpg"/>
   <file href="paddenstoel_stipjes.jpg"/>
   <file href="paddenstoelblauw.jpg"/>
   <file href="paddenstoelgeel.jpg"/>
   <file href="paddenstoelgroen.jpg"/>
   <file href="paddenstoelrood.jpg"/>
   <file href="patroonpaddenstoel1.jpg"/>
   <file href="patroonpaddenstoel2.jpg"/>
   <file href="patroonpaddenstoel3.jpg"/>
   <file href="pictogroot_naar_klein_.jpg"/>
   <file href="project-cover.jpg"/>
   <file href="project-thumb.jpg"/>
   <file href="project.json"/>
   <file href="puzzel6.jpg"/>
  </resource>
 </resources>
</manifest>